[
  {
    "path" : "/",
    "page" : "./pages/home/index.jsx",
    "key" : "index",
    "index" : true
  },
  {
    "path" : "/about",
    "key" : "about",
    "page" : "./pages/about/index.jsx"
  },
  {
    "path" : "/about/product_development",
    "key" : "about_product_development",
    "page" : "./pages/about/product_development/index.jsx"
  },
  {
    "path" : "/about/technology_consulting",
    "key" : "about_technology_consulting",
    "page" : "./pages/about/technology_consulting/index.jsx"
  },
  {
    "path" : "/about/system_integration",
    "key" : "about_system_integration",
    "page" : "./pages/about/system_integration/index.jsx"
  },
  {
    "path" : "/about/hosting_support",
    "key" : "about_hosting_support",
    "page" : "./pages/about/hosting_support/index.jsx"
  },
  {
    "path" : "/about/product_development",
    "key" : "about_product_development",
    "page" : "./pages/about/product_development/index.jsx"
  },
  {
    "path" : "/about/website_startup",
    "key" : "about_website_startup",
    "page" : "./pages/about/website_startup/index.jsx"
  },
  {
    "path" : "/about/custom_application_development",
    "key" : "about_custom_application_development",
    "page" : "./pages/about/custom_application_development/index.jsx"
  },
  {
    "path" : "/error",
    "key" : "error",
    "page" : "./pages/error/index.jsx"
  },
  {
    "path" : "/members",
    "key" : "members",
    "page" : "./pages/members/index.jsx"
  },
  {
    "path" : "/members/tanya",
    "key" : "members_tanya",
    "page" : "./pages/members/tanya/index.jsx"
  },
  {
    "path" : "/members/yomi",
    "key" : "members_yomi",
    "page" : "./pages/members/yomi/index.jsx"
  }
]